asp_chef_cli/__init__.py
asp_chef_cli/__main__.py
asp_chef_cli/cli.py
asp_chef_cli/server/__init__.py
asp_chef_cli/server/dependencies.py
asp_chef_cli/server/main.py
asp_chef_cli/server/routers/__init__.py
asp_chef_cli/server/routers/clingo.py
asp_chef_cli/server/routers/dumbo.py
asp_chef_cli/server/routers/opa.py
asp_chef_cli-0.4.18.dist-info/METADATA
asp_chef_cli-0.4.18.dist-info/WHEEL
asp_chef_cli-0.4.18.dist-info/entry_points.txt
asp_chef_cli-0.4.18.dist-info/licenses/LICENSE
asp_chef_cli-0.4.18.dist-info/RECORD
