Metadata-Version: 2.4
Name: asp-chef-cli
Version: 0.4.18
Summary: A simple CLI to run ASP Chef recipes
License-File: LICENSE
Author: Mario Alviano
Author-email: mario.alviano@gmail.com
Requires-Python: >=3.12,<4.0
Classifier: Programming Language :: Python :: 3
Classifier: Programming Language :: Python :: 3.12
Classifier: Programming Language :: Python :: 3.13
Classifier: Programming Language :: Python :: 3.14
Requires-Dist: dumbo-asp (>=0.3.17,<0.4.0)
Requires-Dist: fastapi (>=0.111.0,<0.112.0)
Requires-Dist: opa-python (>=0.0.9,<0.0.10)
Requires-Dist: pytest-playwright (>=0.5.0,<0.6.0)
Requires-Dist: rich (>=13.4.2,<14.0.0)
Requires-Dist: typer (>=0.12.3,<0.13.0)
Requires-Dist: uvicorn (>=0.30.1,<0.31.0)
